certificate_gen.py
certificate_gen-0.2.dist-info/LICENSE
certificate_gen-0.2.dist-info/METADATA
certificate_gen-0.2.dist-info/WHEEL
certificate_gen-0.2.dist-info/top_level.txt
certificate_gen-0.2.dist-info/RECORD
