Metadata-Version: 2.1
Name: certificate-gen
Version: 0.2
Summary: This is a bulk certificate generator / Mailer package
Home-page: https://github.com/saran-surya/certificate-gen
Author: Saran Surya Ravichandran
Author-email: saransurya199@gmail.com
License: MIT
Keywords: emails certificates bulk e-certificates
Platform: UNKNOWN
Classifier: Development Status :: 4 - Beta
Classifier: Intended Audience :: Developers
Classifier: Topic :: Internet
Classifier: License :: OSI Approved :: GNU Library or Lesser General Public License (LGPL)
Classifier: Programming Language :: Python
Classifier: Programming Language :: Python :: 3
Classifier: Programming Language :: Python :: 3.3
Classifier: Programming Language :: Python :: 3.4
Classifier: Programming Language :: Python :: 3.5
Requires-Python: >=3.6
Requires-Dist: pillow
Requires-Dist: xlrd
